{
  "legislative_session": "2025",
  "identifier": "SB 10",
  "title": "TO AMEND THE ARKANSAS DATA CENTERS ACT OF 2023; AND TO REGULATE THE IMPACT ON WATER USAGE AND THE ELECTRIC GRID BY BLOCKCHAIN NETWORKS AND DIGITAL ASSET MINING.",
  "from_organization": "~{\"classification\": \"upper\"}",
  "classification": [
    "bill"
  ],
  "subject": [],
  "abstracts": [],
  "other_titles": [],
  "other_identifiers": [],
  "actions": [
    {
      "description": "Filed",
      "date": "2024-12-13T20:44:17+00:00",
      "organization_id": "~{\"classification\": \"upper\"}",
      "classification": [
        "introduction"
      ],
      "related_entities": [],
      "_processing": {
        "log_file_created": "2025-10-23T18:01:41Z"
      }
    },
    {
      "description": "Read first time, rules suspended, read second time, referred to CITY, COUNTY & LOCAL AFFAIRS COMMITTEE - SENATE",
      "date": "2025-01-13T19:02:57+00:00",
      "organization_id": "~{\"classification\": \"upper\"}",
      "classification": [
        "reading-1",
        "referral-committee"
      ],
      "related_entities": [],
      "_processing": {
        "log_file_created": "2025-10-23T18:01:41Z"
      }
    },
    {
      "description": "Died in Senate Committee at Sine Die adjournment.",
      "date": "2025-05-05T20:31:35+00:00",
      "organization_id": "~{\"classification\": \"upper\"}",
      "classification": [],
      "related_entities": [],
      "_processing": {
        "log_file_created": "2025-10-23T18:01:41Z"
      }
    }
  ],
  "sponsorships": [
    {
      "name": "B. King",
      "classification": "primary",
      "entity_type": "person",
      "primary": true,
      "person_id": "~{\"chamber\": \"upper\", \"name\": \"B. King\"}",
      "organization_id": null
    }
  ],
  "related_bills": [],
  "versions": [
    {
      "note": "SB 10",
      "links": [
        {
          "url": "https://www.arkleg.state.ar.us/assembly/2025/2025R/Bills/SB10.pdf",
          "media_type": "application/pdf"
        }
      ],
      "date": "",
      "classification": ""
    }
  ],
  "documents": [],
  "citations": [],
  "sources": [
    {
      "url": "https://www.arkleg.state.ar.us/Bills/FTPDocument/?path=%2fSessionInformation%2LegislativeMeasures.txt",
      "note": ""
    },
    {
      "url": "https://www.arkleg.state.ar.us/assembly/2025/2025R/Pages/BillInformation.aspx?measureno=SB10",
      "note": ""
    }
  ],
  "extras": {},
  "jurisdiction": {
    "id": "ocd-jurisdiction/country:us/state:ar/government",
    "name": "Arkansas",
    "classification": "state",
    "division_id": "ocd-division/country:us/state:ar"
  },
  "_processing": {
    "logs_latest_update": "2025-10-23T18:01:41Z",
    "text_extraction_latest_update": "2025-10-24T06:31:03.308959Z"
  }
}