{
  "legislative_session": "2025",
  "identifier": "HR 1083",
  "title": "TO RECOGNIZE THE CATHOLIC HIGH SCHOOL FOR BOYS ROCKETS GOLF TEAM AS THE CLASS 6A STATE CHAMPIONS.",
  "from_organization": "~{\"classification\": \"lower\"}",
  "classification": [
    "resolution"
  ],
  "subject": [],
  "abstracts": [],
  "other_titles": [],
  "other_identifiers": [],
  "actions": [
    {
      "description": "Filed",
      "date": "2025-03-13T21:13:12+00:00",
      "organization_id": "~{\"classification\": \"lower\"}",
      "classification": [
        "introduction"
      ],
      "related_entities": [],
      "_processing": {
        "log_file_created": "2025-10-23T18:01:43Z"
      }
    },
    {
      "description": "Read the first time, rules suspended, read the second time and referred to the Committee on HOUSE MANAGEMENT",
      "date": "2025-03-13T22:25:13+00:00",
      "organization_id": "~{\"classification\": \"lower\"}",
      "classification": [
        "reading-1",
        "reading-2",
        "referral-committee"
      ],
      "related_entities": [],
      "_processing": {
        "log_file_created": "2025-10-23T18:01:43Z"
      }
    },
    {
      "description": "Returned by the Committee Do Pass",
      "date": "2025-03-17T16:12:36+00:00",
      "organization_id": "~{\"classification\": \"lower\"}",
      "classification": [
        "committee-passage"
      ],
      "related_entities": [],
      "_processing": {
        "log_file_created": "2025-10-23T18:01:43Z"
      }
    },
    {
      "description": "READ AND ADOPTED.",
      "date": "2025-04-14T19:08:19+00:00",
      "organization_id": "~{\"classification\": \"lower\"}",
      "classification": [],
      "related_entities": [],
      "_processing": {
        "log_file_created": "2025-10-23T18:01:43Z"
      }
    }
  ],
  "sponsorships": [
    {
      "name": "McCullough",
      "classification": "primary",
      "entity_type": "person",
      "primary": true,
      "person_id": "~{\"chamber\": \"lower\", \"name\": \"McCullough\"}",
      "organization_id": null
    }
  ],
  "related_bills": [],
  "versions": [
    {
      "note": "HR 1083",
      "links": [
        {
          "url": "https://www.arkleg.state.ar.us/assembly/2025/2025R/Bills/HR1083.pdf",
          "media_type": "application/pdf"
        }
      ],
      "date": "",
      "classification": ""
    }
  ],
  "documents": [],
  "citations": [],
  "sources": [
    {
      "url": "https://www.arkleg.state.ar.us/Bills/FTPDocument/?path=%2fSessionInformation%2LegislativeMeasures.txt",
      "note": ""
    },
    {
      "url": "https://www.arkleg.state.ar.us/assembly/2025/2025R/Pages/BillInformation.aspx?measureno=HR1083",
      "note": ""
    }
  ],
  "extras": {},
  "jurisdiction": {
    "id": "ocd-jurisdiction/country:us/state:ar/government",
    "name": "Arkansas",
    "classification": "state",
    "division_id": "ocd-division/country:us/state:ar"
  },
  "_processing": {
    "logs_latest_update": "2025-10-23T18:01:43Z",
    "text_extraction_latest_update": "2025-10-24T05:04:17.930104Z"
  }
}